lyzr/__init__.py
lyzr/__version__.py
lyzr/agents.py
lyzr/base.py
lyzr/context.py
lyzr/exceptions.py
lyzr/http.py
lyzr/image_models.py
lyzr/inference.py
lyzr/knowledge_base_old.py.bak
lyzr/logger.py
lyzr/memory_old.py.bak
lyzr/models_old.py.bak
lyzr/protocols.py
lyzr/providers.py
lyzr/py.typed
lyzr/rai.py
lyzr/responses.py
lyzr/structured.py
lyzr/studio.py
lyzr/urls.py
lyzr/vector_stores.py
lyzr/knowledge_base/__init__.py
lyzr/knowledge_base/config.py
lyzr/knowledge_base/entity.py
lyzr/knowledge_base/models.py
lyzr/knowledge_base/module.py
lyzr/memory/__init__.py
lyzr/memory/config.py
lyzr/memory/entity.py
lyzr/memory/enums.py
lyzr/memory/module.py
lyzr/models/__init__.py
lyzr/models/agent.py
lyzr/models/config.py
lyzr/models/lists.py
lyzr/tools/__init__.py
lyzr/tools/backend.py
lyzr/tools/backend_tools.py
lyzr/tools/decorators.py
lyzr/tools/local.py
sumiki-0.1.2.dist-info/METADATA
sumiki-0.1.2.dist-info/WHEEL
sumiki-0.1.2.dist-info/licenses/LICENSE
sumiki-0.1.2.dist-info/RECORD
