Metadata-Version: 2.4
Name: sumiki
Version: 0.1.2
Summary: Production-ready Python SDK for Lyzr AI Agent Platform - Build intelligent agents with RAG, memory, tools, and guardrails
Project-URL: Homepage, https://lyzr.ai
Project-URL: Documentation, https://docs.lyzr.ai
Project-URL: Repository, https://github.com/lyzr-ai/sumiki
Project-URL: Bug Tracker, https://github.com/lyzr-ai/sumiki/issues
Project-URL: Source Code, https://github.com/lyzr-ai/sumiki
Author-email: Lyzr <support@lyzr.ai>
Maintainer-email: Lyzr <support@lyzr.ai>
License: MIT
License-File: LICENSE
Keywords: agents,ai,ai-agents,anthropic,artificial-intelligence,claude,gemini,gpt,guardrails,llm,lyzr,openai,rag,retrieval-augmented-generation,tool-calling,vector-database
Classifier: Development Status :: 4 - Beta
Classifier: Intended Audience :: Developers
Classifier: License :: OSI Approved :: MIT License
Classifier: Programming Language :: Python :: 3
Classifier: Programming Language :: Python :: 3.8
Classifier: Programming Language :: Python :: 3.9
Classifier: Programming Language :: Python :: 3.10
Classifier: Programming Language :: Python :: 3.11
Classifier: Programming Language :: Python :: 3.12
Classifier: Topic :: Scientific/Engineering :: Artificial Intelligence
Classifier: Topic :: Software Development :: Libraries :: Python Modules
Requires-Python: >=3.8
Requires-Dist: httpx[http2]>=0.24.0
Requires-Dist: json-repair>=0.7.0
Requires-Dist: pydantic>=2.0.0
Requires-Dist: typing-extensions>=4.0.0; python_version < '3.10'
Provides-Extra: dev
Requires-Dist: black>=23.0.0; extra == 'dev'
Requires-Dist: ipython>=8.0.0; extra == 'dev'
Requires-Dist: mypy>=1.0.0; extra == 'dev'
Requires-Dist: pytest-asyncio>=0.21.0; extra == 'dev'
Requires-Dist: pytest-cov>=4.0.0; extra == 'dev'
Requires-Dist: pytest>=7.0.0; extra == 'dev'
Requires-Dist: ruff>=0.1.0; extra == 'dev'
Provides-Extra: jupyter
Requires-Dist: nest-asyncio>=1.5.0; extra == 'jupyter'
